cook/__init__.py
cook/build.py
cook/cli.py
cook/configuration.py
cook/cook.py
cook/exception.py
cook/executors.py
cook/main.py
cook/process.py
cook/recipe.py
cook/rsync.py
cook/sync.py
cook/library/__init__.py
cook/library/key.py
cook/library/logger.py
cook/library/selector.py
cook/library/terminal.py
cook/template/__init__.py
cook/template/recipe_template_1.py
cook/template/recipe_template_2.py
cook/template/recipe_template_3.py
cook/template/recipe_template_4.py
cook_builder-0.4.0.dist-info/licenses/LICENSE
cook_builder-0.4.0.dist-info/METADATA
cook_builder-0.4.0.dist-info/WHEEL
cook_builder-0.4.0.dist-info/entry_points.txt
cook_builder-0.4.0.dist-info/top_level.txt
cook_builder-0.4.0.dist-info/RECORD
