Metadata-Version: 2.4
Name: cook_builder
Version: 0.4.0
Summary: Build script aggregator and remote executor
Author: Seweryn Rusecki
License: MIT License
Project-URL: Homepage, https://github.com/serweryn617/cook
Project-URL: Documentation, https://serweryn617.github.io/cook-docs/
Project-URL: Issues, https://github.com/serweryn617/cook/issues
Classifier: Development Status :: 4 - Beta
Classifier: Environment :: Console
Classifier: Intended Audience :: Developers
Classifier: Topic :: Software Development :: Build Tools
Classifier: Programming Language :: Python :: 3
Classifier: Programming Language :: Python :: 3.10
Classifier: Programming Language :: Python :: 3.11
Classifier: Programming Language :: Python :: 3.12
Classifier: License :: OSI Approved :: MIT License
Classifier: Operating System :: POSIX :: Linux
Requires-Python: >=3.10
License-File: LICENSE
Dynamic: license-file
